py_curate_json/__init__.py
py_curate_json/curate_json_core.py
py_curate_json/flatten_denorm_json.py
py_curate_json-0.1.0.dist-info/DESCRIPTION.rst
py_curate_json-0.1.0.dist-info/METADATA
py_curate_json-0.1.0.dist-info/RECORD
py_curate_json-0.1.0.dist-info/WHEEL
py_curate_json-0.1.0.dist-info/metadata.json
py_curate_json-0.1.0.dist-info/top_level.txt
