Metadata-Version: 2.0
Name: py-curate-json
Version: 0.1.0
Summary: Flatten and Denormalize Hierarchnical JSON Data
Home-page: https://github.com/bundgus/py_curate_json
Author: Mark Bundgus
Author-email: bundgus@gmail.com
License: MIT
